{
    "build": {
      "dockerfilePath": "Dockerfile"
    },
    "start": "java -jar /app.jar",
    "envs": {
      "SPRING_DATASOURCE_URL": {
        "fromPlugin": "postgresql",
        "key": "DATABASE_URL"
      },
      "SPRING_DATASOURCE_USERNAME": {
        "fromPlugin": "postgresql",
        "key": "PGUSER"
      },
      "SPRING_DATASOURCE_PASSWORD": {
        "fromPlugin": "postgresql",
        "key": "PGPASSWORD"
      },
      "SPRING_DATASOURCE_DRIVER_CLASS_NAME": "org.postgresql.Driver"
    }
  }